chard/__init__.py
chard/admin.py
chard/discover.py
chard/exceptions.py
chard/models.py
chard/task.py
chard/types.py
chard/management/__init__.py
chard/management/commands/__init__.py
chard/management/commands/chardworker.py
chard/migrations/0001_initial.py
chard/migrations/__init__.py
django_chard-0.2.dist-info/LICENSE
django_chard-0.2.dist-info/METADATA
django_chard-0.2.dist-info/WHEEL
django_chard-0.2.dist-info/top_level.txt
django_chard-0.2.dist-info/RECORD
