Metadata-Version: 2.1
Name: django-chard
Version: 0.2
Summary: A very simple async/await background task queue for Django.
Home-page: https://github.com/drpancake/chard
Author: James Potter
Author-email: james.potter@gmail.com
Requires-Python: >=3.8
License-File: LICENSE
